helloworld.py
loadImage.py
loadVideo.py
networkRequests.py
utils.py
computer_vision-0.0.6.dist-info/LICENSE
computer_vision-0.0.6.dist-info/METADATA
computer_vision-0.0.6.dist-info/WHEEL
computer_vision-0.0.6.dist-info/top_level.txt
computer_vision-0.0.6.dist-info/RECORD
