Metadata-Version: 2.1
Name: computer-vision
Version: 0.0.6
Summary: Machine Learning utilities to make your Project Development Life easier
Home-page: https://github.com/nishgaba-ai/computer-vision
Author: Nishchal Gaba
Author-email: nishchal@unrealai.xyz
License: UNKNOWN
Platform: UNKNOWN
Classifier: Programming Language :: Python :: 3
Classifier: Programming Language :: Python :: 3.6
Classifier: License :: OSI Approved :: MIT License
Classifier: Operating System :: OS Independent
